pyconindia/__init__.py
pyconindia/__main__.py
pyconindia/cli.py
pyconindia/conference.py
pyconindia/data/conferences.yaml
pyconindia-16.2.5.dist-info/licenses/LICENSE
pyconindia-16.2.5.dist-info/METADATA
pyconindia-16.2.5.dist-info/WHEEL
pyconindia-16.2.5.dist-info/entry_points.txt
pyconindia-16.2.5.dist-info/top_level.txt
pyconindia-16.2.5.dist-info/RECORD
