Metadata-Version: 2.4
Name: pyconindia
Version: 16.2.5
Summary: The largest gathering of Pythonistas in India for the Python programming language.
Home-page: https://github.com/anistark/pyconindia
Author: PyCon India Team
Author-email: PyCon India Team <contact@in.pycon.org>
License: MIT
Project-URL: Homepage, https://in.pycon.org
Project-URL: Repository, https://github.com/anistark/pyconindia
Project-URL: Documentation, https://in.pycon.org
Project-URL: Bug Tracker, https://github.com/anistark/pyconindia/issues
Keywords: python,pycon,conference,india
Classifier: Environment :: Web Environment
Classifier: Environment :: Console
Classifier: Intended Audience :: Developers
Classifier: Programming Language :: Python :: 3
Classifier: Operating System :: OS Independent
Classifier: License :: OSI Approved :: MIT License
Classifier: Topic :: Internet :: WWW/HTTP
Classifier: Topic :: Utilities
Classifier: Topic :: Software Development :: Libraries :: Python Modules
Classifier: Topic :: System :: Shells
Requires-Python: >=3.6
License-File: LICENSE
Requires-Dist: click>=8.0.0
Requires-Dist: PyYAML>=6.0
Provides-Extra: dev
Requires-Dist: pytest>=7.0.0; extra == "dev"
Requires-Dist: black; extra == "dev"
Requires-Dist: flake8; extra == "dev"
Requires-Dist: mypy; extra == "dev"
Dynamic: author
Dynamic: home-page
Dynamic: license-file
Dynamic: requires-python
